Workbook

Sheet Inventory_Report
B2: Seasonal Inventory Analysis (SS26) - Work Sample
B4: Total Units Ordered | F4: Total Forecast Units | I4: Total Cost | L4: Total Forecast Revenue | O4: Total Margin $ | R4: Avg Margin %
B6: =SUM(Seasonal_Buys_CLEAN_data!F2:F994) -> 408 | F6: =SUM(Seasonal_Buys_CLEAN_data!P2:P994) -> 483 | I6: =sum(Seasonal_Buys_CLEAN_data!J2:J994) -> 13611.02 | L6: =sum(Seasonal_Buys_CLEAN_data!T2:T994) -> 16219.3 | O6: =sum(Seasonal_Buys_CLEAN_data!U2:U994) -> 2608.28 | R6: =Average(Seasonal_Buys_CLEAN_data!V2:V994) -> 0.15236685
D9: Item Code | E9: Ordered Units | F9: Forecast Units | R9: BU | S9: Avg Margin
D10: =IFERROR(__xludf.DUMMYFUNCTION("SORT(UNIQUE(FILTER(Seasonal_Buys_CLEAN_data!B2:B994, Seasonal_Buys_CLEAN_data!B2:B994<>"""")))"),1001.0) -> 1001 | E10: =SUMIF(Seasonal_Buys_CLEAN_data!B:B, D10, Seasonal_Buys_CLEAN_data!F:F) -> 110 | F10: =SUMIF(Seasonal_Buys_CLEAN_data!B:B, D10, Seasonal_Buys_CLEAN_data!P:P) -> 120 | R10: =IFERROR(__xludf.DUMMYFUNCTION("UNIQUE(FILTER(Seasonal_Buys_CLEAN_data!A2:A994, Seasonal_Buys_CLEAN_data!A2:A994<>""""))"),"DTC") -> DTC | S10: =AVERAGEIF(Seasonal_Buys_CLEAN_data!A:A, R10, Seasonal_Buys_CLEAN_data!V:V) -> 0.1718546
D11: =IFERROR(__xludf.DUMMYFUNCTION("""COMPUTED_VALUE"""),1002.0) -> 1002 | E11: =SUMIF(Seasonal_Buys_CLEAN_data!B:B, D11, Seasonal_Buys_CLEAN_data!F:F) -> 65 | F11: =SUMIF(Seasonal_Buys_CLEAN_data!B:B, D11, Seasonal_Buys_CLEAN_data!P:P) -> 100 | R11: =IFERROR(__xludf.DUMMYFUNCTION("""COMPUTED_VALUE"""),"WH") -> WH | S11: =AVERAGEIF(Seasonal_Buys_CLEAN_data!A:A, R11, Seasonal_Buys_CLEAN_data!V:V) -> 0.14019331
D12: =IFERROR(__xludf.DUMMYFUNCTION("""COMPUTED_VALUE"""),1003.0) -> 1003 | E12: =SUMIF(Seasonal_Buys_CLEAN_data!B:B, D12, Seasonal_Buys_CLEAN_data!F:F) -> 20 | F12: =SUMIF(Seasonal_Buys_CLEAN_data!B:B, D12, Seasonal_Buys_CLEAN_data!P:P) -> 25 | K12: Stock Status | L12: Count | R12: =IFERROR(__xludf.DUMMYFUNCTION("""COMPUTED_VALUE"""),"INT") -> INT | S12: =AVERAGEIF(Seasonal_Buys_CLEAN_data!A:A, R12, Seasonal_Buys_CLEAN_data!V:V) -> 0.14322409
D13: =IFERROR(__xludf.DUMMYFUNCTION("""COMPUTED_VALUE"""),1004.0) -> 1004 | E13: =SUMIF(Seasonal_Buys_CLEAN_data!B:B, D13, Seasonal_Buys_CLEAN_data!F:F) -> 25 | F13: =SUMIF(Seasonal_Buys_CLEAN_data!B:B, D13, Seasonal_Buys_CLEAN_data!P:P) -> 25 | K13: =IFERROR(__xludf.DUMMYFUNCTION("UNIQUE(FILTER(Seasonal_Buys_CLEAN_data!Q2:Q994, Seasonal_Buys_CLEAN_data!Q2:Q994<>""""))"),"Understock") -> Understock | L13: =COUNTIF(Seasonal_Buys_CLEAN_data!Q:Q, K13) -> 9
D14: =IFERROR(__xludf.DUMMYFUNCTION("""COMPUTED_VALUE"""),1005.0) -> 1005 | E14: =SUMIF(Seasonal_Buys_CLEAN_data!B:B, D14, Seasonal_Buys_CLEAN_data!F:F) -> 15 | F14: =SUMIF(Seasonal_Buys_CLEAN_data!B:B, D14, Seasonal_Buys_CLEAN_data!P:P) -> 20 | K14: =IFERROR(__xludf.DUMMYFUNCTION("""COMPUTED_VALUE"""),"Balanced") -> Balanced | L14: =COUNTIF(Seasonal_Buys_CLEAN_data!Q:Q, K14) -> 5
D15: =IFERROR(__xludf.DUMMYFUNCTION("""COMPUTED_VALUE"""),1006.0) -> 1006 | E15: =SUMIF(Seasonal_Buys_CLEAN_data!B:B, D15, Seasonal_Buys_CLEAN_data!F:F) -> 30 | F15: =SUMIF(Seasonal_Buys_CLEAN_data!B:B, D15, Seasonal_Buys_CLEAN_data!P:P) -> 35
D16: =IFERROR(__xludf.DUMMYFUNCTION("""COMPUTED_VALUE"""),1007.0) -> 1007 | E16: =SUMIF(Seasonal_Buys_CLEAN_data!B:B, D16, Seasonal_Buys_CLEAN_data!F:F) -> 35 | F16: =SUMIF(Seasonal_Buys_CLEAN_data!B:B, D16, Seasonal_Buys_CLEAN_data!P:P) -> 40
D17: =IFERROR(__xludf.DUMMYFUNCTION("""COMPUTED_VALUE"""),1008.0) -> 1008 | E17: =SUMIF(Seasonal_Buys_CLEAN_data!B:B, D17, Seasonal_Buys_CLEAN_data!F:F) -> 25 | F17: =SUMIF(Seasonal_Buys_CLEAN_data!B:B, D17, Seasonal_Buys_CLEAN_data!P:P) -> 25
D18: =IFERROR(__xludf.DUMMYFUNCTION("""COMPUTED_VALUE"""),1009.0) -> 1009 | E18: =SUMIF(Seasonal_Buys_CLEAN_data!B:B, D18, Seasonal_Buys_CLEAN_data!F:F) -> 30 | F18: =SUMIF(Seasonal_Buys_CLEAN_data!B:B, D18, Seasonal_Buys_CLEAN_data!P:P) -> 30
D19: =IFERROR(__xludf.DUMMYFUNCTION("""COMPUTED_VALUE"""),1010.0) -> 1010 | E19: =SUMIF(Seasonal_Buys_CLEAN_data!B:B, D19, Seasonal_Buys_CLEAN_data!F:F) -> 20 | F19: =SUMIF(Seasonal_Buys_CLEAN_data!B:B, D19, Seasonal_Buys_CLEAN_data!P:P) -> 25
D20: =IFERROR(__xludf.DUMMYFUNCTION("""COMPUTED_VALUE"""),1011.0) -> 1011 | E20: =SUMIF(Seasonal_Buys_CLEAN_data!B:B, D20, Seasonal_Buys_CLEAN_data!F:F) -> 15 | F20: =SUMIF(Seasonal_Buys_CLEAN_data!B:B, D20, Seasonal_Buys_CLEAN_data!P:P) -> 20
D21: =IFERROR(__xludf.DUMMYFUNCTION("""COMPUTED_VALUE"""),1012.0) -> 1012 | E21: =SUMIF(Seasonal_Buys_CLEAN_data!B:B, D21, Seasonal_Buys_CLEAN_data!F:F) -> 18 | F21: =SUMIF(Seasonal_Buys_CLEAN_data!B:B, D21, Seasonal_Buys_CLEAN_data!P:P) -> 18
R24: Week Start | S24: Units Arriving
R25: 46182 | S25: =SUMIFS(Seasonal_Buys_CLEAN_data!F:F, Seasonal_Buys_CLEAN_data!N:N, ">="& R25, Seasonal_Buys_CLEAN_data!N:N, "<"& R25+7) -> 150
R26: =R25+7 -> 46189 | S26: =SUMIFS(Seasonal_Buys_CLEAN_data!F:F, Seasonal_Buys_CLEAN_data!N:N, ">="& R26, Seasonal_Buys_CLEAN_data!N:N, "<"& R26+7) -> 243
R27: =R26+7 -> 46196 | S27: =SUMIFS(Seasonal_Buys_CLEAN_data!F:F, Seasonal_Buys_CLEAN_data!N:N, ">="& R27, Seasonal_Buys_CLEAN_data!N:N, "<"& R27+7) -> 15
C28: Understock Priority
C29: BU | D29: Item | E29: Item Description | G29: Category | H29: Ordered | I29: Forecast Units | J29: Variance
C30: INT | D30: 1002 | E30: Floral Dress M | G30: Dresses | H30: 25 | I30: 50 | J30: -25
C31: DTC | D31: 1001 | E31: Floral Dress S | G31: Dresses | H31: 50 | I31: 60 | J31: -10
C32: DTC | D32: 1002 | E32: Floral Dress M | G32: Dresses | H32: 40 | I32: 50 | J32: -10 | L32: Low / Negative Margin Item
C33: WH | D33: 1003 | E33: Denim Jacket L | G33: Jackets | H33: 20 | I33: 25 | J33: -5
C34: WH | D34: 1005 | E34: Silk Blouse S | G34: Tops | H34: 15 | I34: 20 | J34: -5 | L34: BU | M34: Item | N34: Item Description | P34: Total Cost | Q34: Forecast Rev | R34: Margin $ | S34: Margin %
C35: INT | D35: 1006 | E35: Maxi SKirt L | G35: Skirts | H35: 30 | I35: 35 | J35: -5 | L35: INT | M35: 1009 | N35: Summer Dress L | P35: 1059.6 | Q35: 989.7 | R35: -69.9 | S35: -0.070627463
C36: DTC | D36: 1007 | E36: Casual Tee S | G36: Tops | H36: 35 | I36: 40 | J36: -5 | L36: INT | M36: 1012 | N36: Blouse M | P36: 629.82 | Q36: 630 | R36: 0.18 | S36: 0.00028571429
C37: DTC | D37: 1010 | E37: Cardigan M | G37: Jackets | H37: 20 | I37: 25 | J37: -5 | L37: WH | M37: 1008 | N37: Chino Pants M | P37: 874.75 | Q37: 875 | R37: 0.25 | S37: 0.00028571429
C38: WH | D38: 1011 | E38: Wrap Skirt S | G38: Skirts | H38: 15 | I38: 20 | J38: -5 | L38: WH | M38: 1001 | N38: FLoral Dress S | P38: 1799.4 | Q38: 1800 | R38: 0.6 | S38: 0.00033333333
B40: Overview
B42: This report reviews simulated seasonal buys against forecast to identify stock risk, margin exceptions, and planning actions for demonstration of skills. The assortment is underbought versus forecast, creating the primary risk of missed sales. The recommended priority is to chase the largest deficits first, beginning with the INT 1002 (-25), then DTC 1001 and DTC 1002 (-10), followed by the -5 unit group. If inventory exists in other warehouses for shared SKUs, evaluate reroute opportunities. From a profitability standpoint, INT 1009 (-7.06%) requires pricing/cost validation before increasing buys, while the near break-even styles (0.03%) should be monitored closely to prevent margin erosion.

Sheet Seasonal_Buys_CLEAN_data
A1: BU | B1: Item Code | C1: Item Description | D1: Category | E1: Order Qty | F1: Clean Qty | G1: Unit Cost | H1: Clean Unit Cost | I1: Total Cost | J1: Clean Total Cost | K1: PO # | L1: Clean PO # | M1: Delivery Date | N1: Standarized Delivery Dates | O1: Comments | P1: Forecast Units | Q1: Stock Status | R1: Remaining OTB | S1: OTB Status | T1: Forecast Revenue | U1: Margin $ | V1: Margin % | W1: Inventory Action | X1: Qty Variance | Y1: Variance Flag
A2: DTC | B2: 1001 | C2: Floral Dress S | D2: Dresses | E2: 50 | F2: =IF(ISBLANK(E2), VLOOKUP(B2,Sales_Forecast!A:C, 3, FALSE), E2) -> 50 | G2: 29.99 | H2: =IF(ISBLANK(G2), I2/F2, G2) -> 29.99 | I2: 1499.5 | J2: =IF(ISBLANK(I2), F2*H2, I2) -> 1499.5 | K2: PO12345 | L2: =IF(ISBLANK(K2), "PO_TEMP_" & ROW(), K2) -> PO12345 | M2: 46188 | N2: =DATEVALUE(TEXT(M2,"MM/DD/YYYY")) -> 46188 | O2: Late confirmation | P2: =VLOOKUP(B2, Sales_Forecast!A:C, 3, FALSE) -> 60 | Q2: =IF(F2<P2, "Understock", IF(F2>P2, "Overstock", "Balanced")) -> Understock | R2: =VLOOKUP(A2 & "-" & D2, OTB_Budget!A:E, 5, FALSE) -> 12000 | S2: =IF(J2 > R2, "Over Budget", "Within Budget") -> Within Budget | T2: =VLOOKUP(B2, Sales_Forecast!A:D, 4, FALSE) -> 1800 | U2: =T2-J2 -> 300.5 | V2: =U2/T2 -> 0.16694444 | W2: =IF(F2 > P2, "Surplus - Consider Reroute", IF(F2 < P2, "Deficit - Consider Transfer", "Balanced")) -> Deficit - Consider Transfer | X2: =F2-P2 -> -10 | Y2: =IF(X2<0, "Need Units", IF(X2>0, "Excess Units", "On Plan")) -> Need Units
A3: DTC | B3: 1002 | C3: Floral Dress M | D3: Dresses | E3: 40 | F3: =IF(ISBLANK(E3), VLOOKUP(B3,Sales_Forecast!A:C, 3, FALSE), E3) -> 40 | G3: 29.99 | H3: =IF(ISBLANK(G3), I3/F3, G3) -> 29.99 | I3: 1199.6 | J3: =IF(ISBLANK(I3), F3*H3, I3) -> 1199.6 | K3: PO12346 | L3: =IF(ISBLANK(K3), "PO_TEMP_" & ROW(), K3) -> PO12346 | M3: 46188 | N3: =DATEVALUE(TEXT(M3,"MM/DD/YYYY")) -> 46188 | O3: Confirmed | P3: =VLOOKUP(B3, Sales_Forecast!A:C, 3, FALSE) -> 50 | Q3: =IF(F3<P3, "Understock", IF(F3>P3, "Overstock", "Balanced")) -> Understock | R3: =VLOOKUP(A3 & "-" & D3, OTB_Budget!A:E, 5, FALSE) -> 12000 | S3: =IF(J3 > R3, "Over Budget", "Within Budget") -> Within Budget | T3: =VLOOKUP(B3, Sales_Forecast!A:D, 4, FALSE) -> 1500 | U3: =T3-J3 -> 300.4 | V3: =U3/T3 -> 0.20026667 | W3: =IF(F3 > P3, "Surplus - Consider Reroute", IF(F3 < P3, "Deficit - Consider Transfer", "Balanced")) -> Deficit - Consider Transfer | X3: =F3-P3 -> -10 | Y3: =IF(X3<0, "Need Units", IF(X3>0, "Excess Units", "On Plan")) -> Need Units
A4: WH | B4: 1001 | C4: Floral Dress S | D4: Dresses | E4: 60 | F4: =IF(ISBLANK(E4), VLOOKUP(B4,Sales_Forecast!A:C, 3, FALSE), E4) -> 60 | G4: 29.99 | H4: =IF(ISBLANK(G4), I4/F4, G4) -> 29.99 | I4: 1799.4 | J4: =IF(ISBLANK(I4), F4*H4, I4) -> 1799.4 | K4: PO22345 | L4: =IF(ISBLANK(K4), "PO_TEMP_" & ROW(), K4) -> PO22345 | M4: 46187 | N4: =DATEVALUE(TEXT(M4,"MM/DD/YYYY")) -> 46187 | P4: =VLOOKUP(B4, Sales_Forecast!A:C, 3, FALSE) -> 60 | Q4: =IF(F4<P4, "Understock", IF(F4>P4, "Overstock", "Balanced")) -> Balanced | R4: =VLOOKUP(A4 & "-" & D4, OTB_Budget!A:E, 5, FALSE) -> 18000 | S4: =IF(J4 > R4, "Over Budget", "Within Budget") -> Within Budget | T4: =VLOOKUP(B4, Sales_Forecast!A:D, 4, FALSE) -> 1800 | U4: =T4-J4 -> 0.6 | V4: =U4/T4 -> 0.00033333333 | W4: =IF(F4 > P4, "Surplus - Consider Reroute", IF(F4 < P4, "Deficit - Consider Transfer", "Balanced")) -> Balanced | X4: =F4-P4 -> 0 | Y4: =IF(X4<0, "Need Units", IF(X4>0, "Excess Units", "On Plan")) -> On Plan
A5: WH | B5: 1003 | C5: Denim Jacket L | D5: Jackets | E5: 20 | F5: =IF(ISBLANK(E5), VLOOKUP(B5,Sales_Forecast!A:C, 3, FALSE), E5) -> 20 | G5: 49.99 | H5: =IF(ISBLANK(G5), I5/F5, G5) -> 49.99 | I5: 999.8 | J5: =IF(ISBLANK(I5), F5*H5, I5) -> 999.8 | K5: PO22346 | L5: =IF(ISBLANK(K5), "PO_TEMP_" & ROW(), K5) -> PO22346 | M5: 46193 | N5: =DATEVALUE(TEXT(M5,"MM/DD/YYYY")) -> 46193 | P5: =VLOOKUP(B5, Sales_Forecast!A:C, 3, FALSE) -> 25 | Q5: =IF(F5<P5, "Understock", IF(F5>P5, "Overstock", "Balanced")) -> Understock | R5: =VLOOKUP(A5 & "-" & D5, OTB_Budget!A:E, 5, FALSE) -> 7000 | S5: =IF(J5 > R5, "Over Budget", "Within Budget") -> Within Budget | T5: =VLOOKUP(B5, Sales_Forecast!A:D, 4, FALSE) -> 1250 | U5: =T5-J5 -> 250.2 | V5: =U5/T5 -> 0.20016 | W5: =IF(F5 > P5, "Surplus - Consider Reroute", IF(F5 < P5, "Deficit - Consider Transfer", "Balanced")) -> Deficit - Consider Transfer | X5: =F5-P5 -> -5 | Y5: =IF(X5<0, "Need Units", IF(X5>0, "Excess Units", "On Plan")) -> Need Units
A6: INT | B6: 1002 | C6: Floral Dress M | D6: Dresses | E6: 25 | F6: =IF(ISBLANK(E6), VLOOKUP(B6,Sales_Forecast!A:C, 3, FALSE), E6) -> 25 | G6: 29.99 | H6: =IF(ISBLANK(G6), I6/F6, G6) -> 29.99 | I6: 749.75 | J6: =IF(ISBLANK(I6), F6*H6, I6) -> 749.75 | K6: PO32345 | L6: =IF(ISBLANK(K6), "PO_TEMP_" & ROW(), K6) -> PO32345 | M6: 46191 | N6: =DATEVALUE(TEXT(M6,"MM/DD/YYYY")) -> 46191 | P6: =VLOOKUP(B6, Sales_Forecast!A:C, 3, FALSE) -> 50 | Q6: =IF(F6<P6, "Understock", IF(F6>P6, "Overstock", "Balanced")) -> Understock | R6: =VLOOKUP(A6 & "-" & D6, OTB_Budget!A:E, 5, FALSE) -> 9000 | S6: =IF(J6 > R6, "Over Budget", "Within Budget") -> Within Budget | T6: =VLOOKUP(B6, Sales_Forecast!A:D, 4, FALSE) -> 1500 | U6: =T6-J6 -> 750.25 | V6: =U6/T6 -> 0.50016667 | W6: =IF(F6 > P6, "Surplus - Consider Reroute", IF(F6 < P6, "Deficit - Consider Transfer", "Balanced")) -> Deficit - Consider Transfer | X6: =F6-P6 -> -25 | Y6: =IF(X6<0, "Need Units", IF(X6>0, "Excess Units", "On Plan")) -> Need Units
A7: DTC | B7: 1004 | C7: Linen Pants M | D7: Pants | F7: =IF(ISBLANK(E7), VLOOKUP(B7,Sales_Forecast!A:C, 3, FALSE), E7) -> 25 | G7: 34.99 | H7: =IF(ISBLANK(G7), I7/F7, G7) -> 34.99 | I7: 699.8 | J7: =IF(ISBLANK(I7), F7*H7, I7) -> 699.8 | K7: PO12347 | L7: =IF(ISBLANK(K7), "PO_TEMP_" & ROW(), K7) -> PO12347 | M7: 46190 | N7: =DATEVALUE(TEXT(M7,"MM/DD/YYYY")) -> 46190 | O7: Qty missing | P7: =VLOOKUP(B7, Sales_Forecast!A:C, 3, FALSE) -> 25 | Q7: =IF(F7<P7, "Understock", IF(F7>P7, "Overstock", "Balanced")) -> Balanced | R7: =VLOOKUP(A7 & "-" & D7, OTB_Budget!A:E, 5, FALSE) -> 5000 | S7: =IF(J7 > R7, "Over Budget", "Within Budget") -> Within Budget | T7: =VLOOKUP(B7, Sales_Forecast!A:D, 4, FALSE) -> 875 | U7: =T7-J7 -> 175.2 | V7: =U7/T7 -> 0.20022857 | W7: =IF(F7 > P7, "Surplus - Consider Reroute", IF(F7 < P7, "Deficit - Consider Transfer", "Balanced")) -> Balanced | X7: =F7-P7 -> 0 | Y7: =IF(X7<0, "Need Units", IF(X7>0, "Excess Units", "On Plan")) -> On Plan
A8: WH | B8: 1005 | C8: Silk Blouse S | D8: Tops | E8: 15 | F8: =IF(ISBLANK(E8), VLOOKUP(B8,Sales_Forecast!A:C, 3, FALSE), E8) -> 15 | H8: =IF(ISBLANK(G8), I8/F8, G8) -> 40 | I8: 600 | J8: =IF(ISBLANK(I8), F8*H8, I8) -> 600 | K8: PO22347 | L8: =IF(ISBLANK(K8), "PO_TEMP_" & ROW(), K8) -> PO22347 | M8: 46195 | N8: =DATEVALUE(TEXT(M8,"MM/DD/YYYY")) -> 46195 | O8: Unit cost missing | P8: =VLOOKUP(B8, Sales_Forecast!A:C, 3, FALSE) -> 20 | Q8: =IF(F8<P8, "Understock", IF(F8>P8, "Overstock", "Balanced")) -> Understock | R8: =VLOOKUP(A8 & "-" & D8, OTB_Budget!A:E, 5, FALSE) -> 3000 | S8: =IF(J8 > R8, "Over Budget", "Within Budget") -> Within Budget | T8: =VLOOKUP(B8, Sales_Forecast!A:D, 4, FALSE) -> 800 | U8: =T8-J8 -> 200 | V8: =U8/T8 -> 0.25 | W8: =IF(F8 > P8, "Surplus - Consider Reroute", IF(F8 < P8, "Deficit - Consider Transfer", "Balanced")) -> Deficit - Consider Transfer | X8: =F8-P8 -> -5 | Y8: =IF(X8<0, "Need Units", IF(X8>0, "Excess Units", "On Plan")) -> Need Units
A9: INT | B9: 1006 | C9: Maxi Skirt L | D9: Skirts | E9: 30 | F9: =IF(ISBLANK(E9), VLOOKUP(B9,Sales_Forecast!A:C, 3, FALSE), E9) -> 30 | G9: 39.99 | H9: =IF(ISBLANK(G9), I9/F9, G9) -> 39.99 | I9: 1199.7 | J9: =IF(ISBLANK(I9), F9*H9, I9) -> 1199.7 | L9: =IF(ISBLANK(K9), "PO_TEMP_" & ROW(), K9) -> PO_TEMP_9 | M9: 46192 | N9: =DATEVALUE(TEXT(M9,"MM/DD/YYYY")) -> 46192 | O9: PO # missing | P9: =VLOOKUP(B9, Sales_Forecast!A:C, 3, FALSE) -> 35 | Q9: =IF(F9<P9, "Understock", IF(F9>P9, "Overstock", "Balanced")) -> Understock | R9: =VLOOKUP(A9 & "-" & D9, OTB_Budget!A:E, 5, FALSE) -> 2000 | S9: =IF(J9 > R9, "Over Budget", "Within Budget") -> Within Budget | T9: =VLOOKUP(B9, Sales_Forecast!A:D, 4, FALSE) -> 1400 | U9: =T9-J9 -> 200.3 | V9: =U9/T9 -> 0.14307143 | W9: =IF(F9 > P9, "Surplus - Consider Reroute", IF(F9 < P9, "Deficit - Consider Transfer", "Balanced")) -> Deficit - Consider Transfer | X9: =F9-P9 -> -5 | Y9: =IF(X9<0, "Need Units", IF(X9>0, "Excess Units", "On Plan")) -> Need Units
A10: DTC | B10: 1007 | C10: Casual Tee S | D10: Tops | E10: 35 | F10: =IF(ISBLANK(E10), VLOOKUP(B10,Sales_Forecast!A:C, 3, FALSE), E10) -> 35 | G10: 19.99 | H10: =IF(ISBLANK(G10), I10/F10, G10) -> 19.99 | I10: 699.65 | J10: =IF(ISBLANK(I10), F10*H10, I10) -> 699.65 | K10: PO12348 | L10: =IF(ISBLANK(K10), "PO_TEMP_" & ROW(), K10) -> PO12348 | M10: 46189 | N10: =DATEVALUE(TEXT(M10,"MM/DD/YYYY")) -> 46189 | P10: =VLOOKUP(B10, Sales_Forecast!A:C, 3, FALSE) -> 40 | Q10: =IF(F10<P10, "Understock", IF(F10>P10, "Overstock", "Balanced")) -> Understock | R10: =VLOOKUP(A10 & "-" & D10, OTB_Budget!A:E, 5, FALSE) -> 3000 | S10: =IF(J10 > R10, "Over Budget", "Within Budget") -> Within Budget | T10: =VLOOKUP(B10, Sales_Forecast!A:D, 4, FALSE) -> 799.6 | U10: =T10-J10 -> 99.95 | V10: =U10/T10 -> 0.125 | W10: =IF(F10 > P10, "Surplus - Consider Reroute", IF(F10 < P10, "Deficit - Consider Transfer", "Balanced")) -> Deficit - Consider Transfer | X10: =F10-P10 -> -5 | Y10: =IF(X10<0, "Need Units", IF(X10>0, "Excess Units", "On Plan")) -> Need Units
A11: WH | B11: 1008 | C11: Chino Pants M | D11: Pants | E11: 25 | F11: =IF(ISBLANK(E11), VLOOKUP(B11,Sales_Forecast!A:C, 3, FALSE), E11) -> 25 | G11: 34.99 | H11: =IF(ISBLANK(G11), I11/F11, G11) -> 34.99 | I11: 874.75 | J11: =IF(ISBLANK(I11), F11*H11, I11) -> 874.75 | K11: PO22348 | L11: =IF(ISBLANK(K11), "PO_TEMP_" & ROW(), K11) -> PO22348 | M11: 46194 | N11: =DATEVALUE(TEXT(M11,"MM/DD/YYYY")) -> 46194 | P11: =VLOOKUP(B11, Sales_Forecast!A:C, 3, FALSE) -> 25 | Q11: =IF(F11<P11, "Understock", IF(F11>P11, "Overstock", "Balanced")) -> Balanced | R11: =VLOOKUP(A11 & "-" & D11, OTB_Budget!A:E, 5, FALSE) -> 4000 | S11: =IF(J11 > R11, "Over Budget", "Within Budget") -> Within Budget | T11: =VLOOKUP(B11, Sales_Forecast!A:D, 4, FALSE) -> 875 | U11: =T11-J11 -> 0.25 | V11: =U11/T11 -> 0.00028571429 | W11: =IF(F11 > P11, "Surplus - Consider Reroute", IF(F11 < P11, "Deficit - Consider Transfer", "Balanced")) -> Balanced | X11: =F11-P11 -> 0 | Y11: =IF(X11<0, "Need Units", IF(X11>0, "Excess Units", "On Plan")) -> On Plan
A12: INT | B12: 1009 | C12: Summer Dress L | D12: Dresses | F12: =IF(ISBLANK(E12), VLOOKUP(B12,Sales_Forecast!A:C, 3, FALSE), E12) -> 30 | G12: 32.99 | H12: =IF(ISBLANK(G12), I12/F12, G12) -> 32.99 | I12: 1059.6 | J12: =IF(ISBLANK(I12), F12*H12, I12) -> 1059.6 | K12: PO32347 | L12: =IF(ISBLANK(K12), "PO_TEMP_" & ROW(), K12) -> PO32347 | M12: 46193 | N12: =DATEVALUE(TEXT(M12,"MM/DD/YYYY")) -> 46193 | O12: Qty missing | P12: =VLOOKUP(B12, Sales_Forecast!A:C, 3, FALSE) -> 30 | Q12: =IF(F12<P12, "Understock", IF(F12>P12, "Overstock", "Balanced")) -> Balanced | R12: =VLOOKUP(A12 & "-" & D12, OTB_Budget!A:E, 5, FALSE) -> 9000 | S12: =IF(J12 > R12, "Over Budget", "Within Budget") -> Within Budget | T12: =VLOOKUP(B12, Sales_Forecast!A:D, 4, FALSE) -> 989.7 | U12: =T12-J12 -> -69.9 | V12: =U12/T12 -> -0.070627463 | W12: =IF(F12 > P12, "Surplus - Consider Reroute", IF(F12 < P12, "Deficit - Consider Transfer", "Balanced")) -> Balanced | X12: =F12-P12 -> 0 | Y12: =IF(X12<0, "Need Units", IF(X12>0, "Excess Units", "On Plan")) -> On Plan
A13: DTC | B13: 1010 | C13: Cardigan M | D13: Jackets | E13: 20 | F13: =IF(ISBLANK(E13), VLOOKUP(B13,Sales_Forecast!A:C, 3, FALSE), E13) -> 20 | G13: 49.99 | H13: =IF(ISBLANK(G13), I13/F13, G13) -> 49.99 | J13: =IF(ISBLANK(I13), F13*H13, I13) -> 999.8 | K13: PO12349 | L13: =IF(ISBLANK(K13), "PO_TEMP_" & ROW(), K13) -> PO12349 | M13: 46191 | N13: =DATEVALUE(TEXT(M13,"MM/DD/YYYY")) -> 46191 | O13: Total cost missing | P13: =VLOOKUP(B13, Sales_Forecast!A:C, 3, FALSE) -> 25 | Q13: =IF(F13<P13, "Understock", IF(F13>P13, "Overstock", "Balanced")) -> Understock | R13: =VLOOKUP(A13 & "-" & D13, OTB_Budget!A:E, 5, FALSE) -> 7500 | S13: =IF(J13 > R13, "Over Budget", "Within Budget") -> Within Budget | T13: =VLOOKUP(B13, Sales_Forecast!A:D, 4, FALSE) -> 1200 | U13: =T13-J13 -> 200.2 | V13: =U13/T13 -> 0.16683333 | W13: =IF(F13 > P13, "Surplus - Consider Reroute", IF(F13 < P13, "Deficit - Consider Transfer", "Balanced")) -> Deficit - Consider Transfer | X13: =F13-P13 -> -5 | Y13: =IF(X13<0, "Need Units", IF(X13>0, "Excess Units", "On Plan")) -> Need Units
A14: WH | B14: 1011 | C14: Wrap Skirt S | D14: Skirts | E14: 15 | F14: =IF(ISBLANK(E14), VLOOKUP(B14,Sales_Forecast!A:C, 3, FALSE), E14) -> 15 | G14: 39.99 | H14: =IF(ISBLANK(G14), I14/F14, G14) -> 39.99 | I14: 599.85 | J14: =IF(ISBLANK(I14), F14*H14, I14) -> 599.85 | K14: PO22349 | L14: =IF(ISBLANK(K14), "PO_TEMP_" & ROW(), K14) -> PO22349 | M14: 46196 | N14: =DATEVALUE(TEXT(M14,"MM/DD/YYYY")) -> 46196 | P14: =VLOOKUP(B14, Sales_Forecast!A:C, 3, FALSE) -> 20 | Q14: =IF(F14<P14, "Understock", IF(F14>P14, "Overstock", "Balanced")) -> Understock | R14: =VLOOKUP(A14 & "-" & D14, OTB_Budget!A:E, 5, FALSE) -> 3000 | S14: =IF(J14 > R14, "Over Budget", "Within Budget") -> Within Budget | T14: =VLOOKUP(B14, Sales_Forecast!A:D, 4, FALSE) -> 800 | U14: =T14-J14 -> 200.15 | V14: =U14/T14 -> 0.2501875 | W14: =IF(F14 > P14, "Surplus - Consider Reroute", IF(F14 < P14, "Deficit - Consider Transfer", "Balanced")) -> Deficit - Consider Transfer | X14: =F14-P14 -> -5 | Y14: =IF(X14<0, "Need Units", IF(X14>0, "Excess Units", "On Plan")) -> Need Units
A15: INT | B15: 1012 | C15: Blouse M | D15: Tops | E15: 18 | F15: =IF(ISBLANK(E15), VLOOKUP(B15,Sales_Forecast!A:C, 3, FALSE), E15) -> 18 | G15: 34.99 | H15: =IF(ISBLANK(G15), I15/F15, G15) -> 34.99 | I15: 629.82 | J15: =IF(ISBLANK(I15), F15*H15, I15) -> 629.82 | K15: PO32348 | L15: =IF(ISBLANK(K15), "PO_TEMP_" & ROW(), K15) -> PO32348 | M15: 46192 | N15: =DATEVALUE(TEXT(M15,"MM/DD/YYYY")) -> 46192 | P15: =VLOOKUP(B15, Sales_Forecast!A:C, 3, FALSE) -> 18 | Q15: =IF(F15<P15, "Understock", IF(F15>P15, "Overstock", "Balanced")) -> Balanced | R15: =VLOOKUP(A15 & "-" & D15, OTB_Budget!A:E, 5, FALSE) -> 2000 | S15: =IF(J15 > R15, "Over Budget", "Within Budget") -> Within Budget | T15: =VLOOKUP(B15, Sales_Forecast!A:D, 4, FALSE) -> 630 | U15: =T15-J15 -> 0.18 | V15: =U15/T15 -> 0.00028571429 | W15: =IF(F15 > P15, "Surplus - Consider Reroute", IF(F15 < P15, "Deficit - Consider Transfer", "Balanced")) -> Balanced | X15: =F15-P15 -> 0 | Y15: =IF(X15<0, "Need Units", IF(X15>0, "Excess Units", "On Plan")) -> On Plan

Sheet Seasonal_Buys_Pivot Table

Sheet BU_Insights_Pivot Table

Sheet Seasonal_Buys_MESSY_data
A1: BU | B1: Item Code | C1: Item Description | D1: Category | E1: Order Qty | F1: Unit Cost | G1: Total Cost | H1: PO # | I1: Delivery Date | J1: Comments
A2: DTC | B2: 1001 | C2: Floral Dress S | D2: Dresses | E2: 50 | F2: 29.99 | G2: 1499.5 | H2: PO12345 | I2: 46188 | J2: Late confirmation
A3: DTC | B3: 1002 | C3: Floral Dress M | D3: Dresses | E3: 40 | F3: 29.99 | G3: 1199.6 | H3: PO12346 | I3: 46188 | J3: Confirmed
A4: WH | B4: 1001 | C4: Floral Dress S | D4: Dresses | E4: 60 | F4: 29.99 | G4: 1799.4 | H4: PO22345 | I4: 46187
A5: WH | B5: 1003 | C5: Denim Jacket L | D5: Jackets | E5: 20 | F5: 49.99 | G5: 999.8 | H5: PO22346 | I5: 46193
A6: INT | B6: 1002 | C6: Floral Dress M | D6: Dresses | E6: 25 | F6: 29.99 | G6: 749.75 | H6: PO32345 | I6: 46191
A7: DTC | B7: 1004 | C7: Linen Pants M | D7: Pants | F7: 34.99 | G7: 699.8 | H7: PO12347 | I7: 46190 | J7: Qty missing
A8: WH | B8: 1005 | C8: Silk Blouse S | D8: Tops | E8: 15 | G8: 600 | H8: PO22347 | I8: 46195 | J8: Unit cost missing
A9: INT | B9: 1006 | C9: Maxi Skirt L | D9: Skirts | E9: 30 | F9: 39.99 | G9: 1199.7 | I9: 46192 | J9: PO # missing
A10: DTC | B10: 1007 | C10: Casual Tee S | D10: Tops | E10: 35 | F10: 19.99 | G10: 699.65 | H10: PO12348 | I10: 46189
A11: WH | B11: 1008 | C11: Chino Pants M | D11: Pants | E11: 25 | F11: 34.99 | G11: 874.75 | H11: PO22348 | I11: 46194
A12: INT | B12: 1009 | C12: Summer Dress L | D12: Dresses | F12: 32.99 | G12: 1059.6 | H12: PO32347 | I12: 46193 | J12: Qty missing
A13: DTC | B13: 1010 | C13: Cardigan M | D13: Jackets | E13: 20 | F13: 49.99 | H13: PO12349 | I13: 46191 | J13: Total cost missing
A14: WH | B14: 1011 | C14: Wrap Skirt S | D14: Skirts | E14: 15 | F14: 39.99 | G14: 599.85 | H14: PO22349 | I14: 46196
A15: INT | B15: 1012 | C15: Blouse M | D15: Tops | E15: 18 | F15: 34.99 | G15: 629.82 | H15: PO32348 | I15: 46192

Sheet OTB_Budget
A1: BU_Category_Key | B1: BU | C1: Category | D1: OTB Limit | E1: Current Spend | F1: Remaining OTB
A2: =B1:B2 & "-" & C2 -> DTC-Dresses | B2: DTC | C2: Dresses | D2: 20000 | E2: 12000 | F2: 8000
A3: =B2:B3 & "-" & C3 -> DTC-Pants | B3: DTC | C3: Pants | D3: 10000 | E3: 5000 | F3: 5000
A4: =B3:B4 & "-" & C4 -> DTC-Jackets | B4: DTC | C4: Jackets | D4: 15000 | E4: 7500 | F4: 7500
A5: =B4:B5 & "-" & C5 -> DTC-Tops | B5: DTC | C5: Tops | D5: 7000 | E5: 3000 | F5: 4000
A6: =B5:B6 & "-" & C6 -> WH-Dresses | B6: WH | C6: Dresses | D6: 25000 | E6: 18000 | F6: 7000
A7: =B6:B7 & "-" & C7 -> WH-Jackets | B7: WH | C7: Jackets | D7: 12000 | E7: 7000 | F7: 5000
A8: =B7:B8 & "-" & C8 -> WH-Pants | B8: WH | C8: Pants | D8: 10000 | E8: 4000 | F8: 6000
A9: =B8:B9 & "-" & C9 -> WH-Skirts | B9: WH | C9: Skirts | D9: 8000 | E9: 3000 | F9: 5000
A10: =B9:B10 & "-" & C10 -> WH-Tops | B10: WH | C10: Tops | D10: 7000 | E10: 3000 | F10: 4000
A11: =B10:B11 & "-" & C11 -> INT-Dresses | B11: INT | C11: Dresses | D11: 15000 | E11: 9000 | F11: 6000
A12: =B11:B12 & "-" & C12 -> INT-Skirts | B12: INT | C12: Skirts | D12: 10000 | E12: 2000 | F12: 8000
A13: =B12:B13 & "-" & C13 -> INT-Tops | B13: INT | C13: Tops | D13: 6000 | E13: 2000 | F13: 4000
A14: =B13:B14 & "-" & C14 -> INT-Pants | B14: INT | C14: Pants | D14: 5000 | E14: 1000 | F14: 4000

Sheet Sales_Forecast
A1: Item Code | B1: BU | C1: Forecast Units | D1: Forecast Revenue | E1: Margin %
A2: 1001 | B2: DTC | C2: 60 | D2: 1800 | E2: 0.6
A3: 1002 | B3: DTC | C3: 50 | D3: 1500 | E3: 0.55
A4: 1001 | B4: WH | C4: 70 | D4: 2100 | E4: 0.5
A5: 1003 | B5: WH | C5: 25 | D5: 1250 | E5: 0.52
A6: 1002 | B6: INT | C6: 30 | D6: 900 | E6: 0.5
A7: 1004 | B7: DTC | C7: 25 | D7: 875 | E7: 0.6
A8: 1005 | B8: WH | C8: 20 | D8: 800 | E8: 0.55
A9: 1006 | B9: INT | C9: 35 | D9: 1400 | E9: 0.48
A10: 1007 | B10: DTC | C10: 40 | D10: 799.6 | E10: 0.55
A11: 1008 | B11: WH | C11: 25 | D11: 875 | E11: 0.5
A12: 1009 | B12: INT | C12: 30 | D12: 989.7 | E12: 0.52
A13: 1010 | B13: DTC | C13: 25 | D13: 1200 | E13: 0.5
... A15: 1012 | B15: INT | C15: 18 | D15: 630 | E15: 0.55
